nuwa_pytorch/__init__.py
nuwa_pytorch/image_utils.py
nuwa_pytorch/nuwa_pytorch.py
nuwa_pytorch/optimizer.py
nuwa_pytorch/reversible.py
nuwa_pytorch/reversible_video_audio.py
nuwa_pytorch/tokenizer.py
nuwa_pytorch/train_nuwa.py
nuwa_pytorch/train_vqgan_vae.py
nuwa_pytorch/vqgan_vae.py
nuwa_pytorch/data/bpe_simple_vocab_16e6.txt
nuwa_pytorch-0.7.8.dist-info/LICENSE
nuwa_pytorch-0.7.8.dist-info/METADATA
nuwa_pytorch-0.7.8.dist-info/WHEEL
nuwa_pytorch-0.7.8.dist-info/top_level.txt
nuwa_pytorch-0.7.8.dist-info/RECORD
