Metadata-Version: 2.1
Name: nuwa-pytorch
Version: 0.7.8
Summary: NÜWA - Pytorch
Home-page: https://github.com/lucidrains/nuwa-pytorch
Author: Phil Wang
Author-email: lucidrains@gmail.com
License: MIT
Keywords: artificial intelligence,attention mechanism,transformers
Classifier: Development Status :: 4 - Beta
Classifier: Intended Audience :: Developers
Classifier: Topic :: Scientific/Engineering :: Artificial Intelligence
Classifier: License :: OSI Approved :: MIT License
Classifier: Programming Language :: Python :: 3.6
License-File: LICENSE
Requires-Dist: einops (>=0.4.1)
Requires-Dist: ftfy
Requires-Dist: pillow
Requires-Dist: regex
Requires-Dist: torch (>=1.6)
Requires-Dist: torchvision
Requires-Dist: tqdm
Requires-Dist: unfoldNd
Requires-Dist: vector-quantize-pytorch (>=0.4.10)
